<coordinates>
<latlng>81.5460205078126,21.3314304351807</latlng>
<latlng>81.5474472045898,21.3335781097412</latlng>
<latlng>81.5506286621095,21.3349609375</latlng>
<latlng>81.5577316284179,21.3359107971193</latlng>
<latlng>81.5612564086915,21.3361911773682</latlng>
<latlng>81.5668563842775,21.3336906433105</latlng>
<latlng>81.5726318359375,21.3327903747559</latlng>
<latlng>81.578468322754,21.3343200683595</latlng>
<latlng>81.5861663818359,21.3414897918702</latlng>
<latlng>81.5893096923829,21.3458003997803</latlng>
<latlng>81.5874099731446,21.3556880950928</latlng>
<latlng>81.5889129638672,21.3586597442627</latlng>
<latlng>81.599449157715,21.3618202209473</latlng>
<latlng>81.6024017333984,21.3631801605225</latlng>
<latlng>81.6047363281251,21.3658409118653</latlng>
<latlng>81.6061477661134,21.3719501495362</latlng>
<latlng>81.6039810180665,21.3790111541749</latlng>
<latlng>81.6040267944337,21.3822212219239</latlng>
<latlng>81.6092224121093,21.3858509063722</latlng>
<latlng>81.6194992065431,21.3861198425294</latlng>
<latlng>81.6222229003906,21.388729095459</latlng>
<latlng>81.6321868896485,21.4027099609376</latlng>
<latlng>81.6318817138673,21.4056797027589</latlng>
<latlng>81.6267318725587,21.4110698699952</latlng>
<latlng>81.6250762939453,21.4148197174073</latlng>
<latlng>81.6259689331056,21.4247703552247</latlng>
<latlng>81.6239395141602,21.4335098266603</latlng>
<latlng>81.6263427734376,21.4410705566407</latlng>
<latlng>81.6260223388672,21.4449806213379</latlng>
<latlng>81.6199417114258,21.4531707763671</latlng>
<latlng>81.6181564331056,21.4633197784425</latlng>
<latlng>81.6190567016602,21.4670295715332</latlng>
<latlng>81.6248626708984,21.4734611511232</latlng>
<latlng>81.6237487792969,21.4834308624268</latlng>
<latlng>81.6247787475587,21.5048999786378</latlng>
<latlng>81.6276473999024,21.510181427002</latlng>
<latlng>81.6384429931641,21.5184497833251</latlng>
<latlng>81.6389923095703,21.5254306793213</latlng>
<latlng>81.6371459960938,21.5405311584473</latlng>
<latlng>81.6382904052735,21.5442981719971</latlng>
<latlng>81.6451568603516,21.5458908081055</latlng>
<latlng>81.6616516113282,21.5443897247314</latlng>
<latlng>81.662712097168,21.5470008850098</latlng>
<latlng>81.6629867553712,21.5513496398926</latlng>
<latlng>81.6616287231446,21.5641212463379</latlng>
<latlng>81.6642227172852,21.567190170288</latlng>
<latlng>81.6720886230469,21.5706882476808</latlng>
<latlng>81.6763458251954,21.5743904113769</latlng>
<latlng>81.6789627075196,21.58304977417</latlng>
<latlng>81.6867828369141,21.5944118499757</latlng>
<latlng>81.6952362060548,21.58597946167</latlng>
<latlng>81.7004089355469,21.5841827392579</latlng>
<latlng>81.7076873779297,21.5849990844727</latlng>
<latlng>81.7137985229492,21.584421157837</latlng>
<latlng>81.7329025268555,21.5779800415039</latlng>
<latlng>81.7412872314454,21.5783596038819</latlng>
<latlng>81.750328063965,21.5833110809327</latlng>
<latlng>81.7468795776368,21.5860996246338</latlng>
<latlng>81.7430496215821,21.5878982543945</latlng>
<latlng>81.7397384643555,21.5915718078613</latlng>
<latlng>81.7376327514648,21.5947494506836</latlng>
<latlng>81.7374114990234,21.6023197174073</latlng>
<latlng>81.7439270019531,21.6025524139405</latlng>
<latlng>81.74658203125,21.6092700958252</latlng>
<latlng>81.7492599487305,21.6093082427979</latlng>
<latlng>81.7653961181642,21.6035919189454</latlng>
<latlng>81.769660949707,21.6075916290283</latlng>
<latlng>81.777572631836,21.6190299987793</latlng>
<latlng>81.7805862426758,21.6222496032716</latlng>
<latlng>81.7838363647462,21.619691848755</latlng>
<latlng>81.7825164794922,21.6046504974366</latlng>
<latlng>81.7836685180665,21.5974197387695</latlng>
<latlng>81.7863693237306,21.5939712524414</latlng>
<latlng>81.7934494018556,21.592140197754</latlng>
<latlng>81.8105926513673,21.5938282012939</latlng>
<latlng>81.8219909667969,21.5939903259278</latlng>
<latlng>81.8287658691406,21.5935592651367</latlng>
<latlng>81.8340072631837,21.5916805267335</latlng>
<latlng>81.8395309448243,21.5924301147461</latlng>
<latlng>81.8487167358399,21.6010417938233</latlng>
<latlng>81.8532180786133,21.6030502319337</latlng>
<latlng>81.8584365844727,21.6015205383301</latlng>
<latlng>81.8598480224609,21.5970096588136</latlng>
<latlng>81.8589401245117,21.5913028717042</latlng>
<latlng>81.8597183227539,21.5892295837403</latlng>
<latlng>81.8662109375,21.5867176055909</latlng>
<latlng>81.873420715332,21.5819110870362</latlng>
<latlng>81.8771133422852,21.5774402618408</latlng>
<latlng>81.8802719116211,21.5710811614991</latlng>
<latlng>81.8847732543946,21.5690803527832</latlng>
<latlng>81.8874130249024,21.5695705413819</latlng>
<latlng>81.8905029296876,21.5738410949707</latlng>
<latlng>81.8984527587891,21.5934104919435</latlng>
<latlng>81.9134521484374,21.589750289917</latlng>
<latlng>81.9190826416016,21.5864295959473</latlng>
<latlng>81.9245223999023,21.5819911956788</latlng>
<latlng>81.9271697998048,21.5787601470947</latlng>
<latlng>81.9289627075195,21.574499130249</latlng>
<latlng>81.9296875,21.569658279419</latlng>
<latlng>81.9327926635743,21.5668010711669</latlng>
<latlng>81.9287567138672,21.5592498779297</latlng>
<latlng>81.9254989624023,21.5558204650879</latlng>
<latlng>81.9211273193359,21.5485782623292</latlng>
<latlng>81.9215698242188,21.5442008972169</latlng>
<latlng>81.9239959716797,21.5357398986817</latlng>
<latlng>81.9327697753906,21.518440246582</latlng>
<latlng>81.9282989501954,21.5062007904053</latlng>
<latlng>81.9262771606445,21.4988403320313</latlng>
<latlng>81.9264678955078,21.4940929412843</latlng>
<latlng>81.9283294677734,21.4903602600098</latlng>
<latlng>81.9331588745117,21.4851818084717</latlng>
<latlng>81.9381713867188,21.4832401275635</latlng>
<latlng>81.9419326782227,21.4832897186279</latlng>
<latlng>81.9516906738282,21.4857006072999</latlng>
<latlng>81.9504470825195,21.4757499694825</latlng>
<latlng>81.9505310058594,21.4730091094972</latlng>
<latlng>81.9499664306641,21.4703216552736</latlng>
<latlng>81.956428527832,21.4689598083496</latlng>
<latlng>81.9640579223633,21.4696502685547</latlng>
<latlng>81.9713973999025,21.4707202911378</latlng>
<latlng>81.9772109985352,21.4714183807374</latlng>
<latlng>81.9791793823243,21.4728298187256</latlng>
<latlng>81.9812164306641,21.4729194641113</latlng>
<latlng>81.9829330444336,21.4725208282471</latlng>
<latlng>81.9847717285157,21.4715900421143</latlng>
<latlng>81.9847564697267,21.4714107513429</latlng>
<latlng>81.9848022460938,21.4708194732666</latlng>
<latlng>81.9848632812501,21.470220565796</latlng>
<latlng>81.98494720459,21.4696426391602</latlng>
<latlng>81.9850463867188,21.4690608978272</latlng>
<latlng>81.9851608276367,21.4684906005859</latlng>
<latlng>81.9852981567384,21.467929840088</latlng>
<latlng>81.9854812622071,21.4673728942872</latlng>
<latlng>81.9856719970704,21.4668407440187</latlng>
<latlng>81.9858627319337,21.4663085937501</latlng>
<latlng>81.9861068725587,21.4657897949219</latlng>
<latlng>81.9863510131836,21.46529006958</latlng>
<latlng>81.9866104125977,21.4647884368896</latlng>
<latlng>81.9868927001953,21.4643115997314</latlng>
<latlng>81.9872207641603,21.4638404846192</latlng>
<latlng>81.9875259399415,21.4633808135986</latlng>
<latlng>81.9878387451171,21.4629402160646</latlng>
<latlng>81.9882431030273,21.4625225067139</latlng>
<latlng>81.9886169433594,21.4620876312255</latlng>
<latlng>81.9889984130859,21.4616928100587</latlng>
<latlng>81.9894104003906,21.4612903594971</latlng>
<latlng>81.9898529052735,21.4609107971191</latlng>
<latlng>81.9903030395509,21.4605503082276</latlng>
<latlng>81.9907531738281,21.4602012634277</latlng>
<latlng>81.9912185668946,21.4598598480225</latlng>
<latlng>81.9917068481445,21.4595298767091</latlng>
<latlng>81.9922103881837,21.4592304229737</latlng>
<latlng>81.9929275512696,21.4592399597168</latlng>
<latlng>82.0029296875,21.4552726745606</latlng>
<latlng>82.0132369995117,21.4498596191407</latlng>
<latlng>82.0264358520508,21.4556903839112</latlng>
<latlng>82.0339660644532,21.4461975097657</latlng>
<latlng>82.0471267700196,21.4395828247071</latlng>
<latlng>82.0567016601562,21.4353904724121</latlng>
<latlng>82.0773468017578,21.4333381652833</latlng>
<latlng>82.0839767456055,21.4299812316896</latlng>
<latlng>82.0905380249024,21.4229812622071</latlng>
<latlng>82.0971527099609,21.4174804687501</latlng>
<latlng>82.1032180786134,21.4157810211183</latlng>
<latlng>82.1173782348633,21.4095325469972</latlng>
<latlng>82.1137466430664,21.3984394073487</latlng>
<latlng>82.1128158569336,21.3836784362793</latlng>
<latlng>82.1218719482423,21.3787708282471</latlng>
<latlng>82.1227188110352,21.371940612793</latlng>
<latlng>82.1264877319337,21.3678016662599</latlng>
<latlng>82.132179260254,21.3654708862305</latlng>
<latlng>82.1375427246095,21.3622817993165</latlng>
<latlng>82.1437988281251,21.3624229431153</latlng>
<latlng>82.147346496582,21.3679199218749</latlng>
<latlng>82.1623687744141,21.3786201477051</latlng>
<latlng>82.170639038086,21.3807601928711</latlng>
<latlng>82.1841659545898,21.374891281128</latlng>
<latlng>82.1868286132812,21.3755702972413</latlng>
<latlng>82.1845397949219,21.3689117431641</latlng>
<latlng>82.1818389892578,21.3639812469483</latlng>
<latlng>82.1741790771484,21.355489730835</latlng>
<latlng>82.1730422973632,21.3462696075439</latlng>
<latlng>82.1626205444337,21.3326797485352</latlng>
<latlng>82.1588668823243,21.32546043396</latlng>
<latlng>82.1470489501954,21.3196811676027</latlng>
<latlng>82.1342773437501,21.3042106628419</latlng>
<latlng>82.1279525756837,21.2985305786133</latlng>
<latlng>82.1208267211914,21.2936096191407</latlng>
<latlng>82.1112365722656,21.2886505126954</latlng>
<latlng>82.1005783081055,21.2857398986817</latlng>
<latlng>82.0691680908204,21.2737998962402</latlng>
<latlng>82.0609893798829,21.2688312530518</latlng>
<latlng>82.0202865600586,21.2302799224854</latlng>
<latlng>82.0170593261719,21.2262210845948</latlng>
<latlng>82.0123367309571,21.2169780731202</latlng>
<latlng>82.0135879516601,21.1828899383545</latlng>
<latlng>82.0119628906251,21.1702919006348</latlng>
<latlng>82.0087280273438,21.1587810516359</latlng>
<latlng>82.0043563842774,21.1496810913087</latlng>
<latlng>81.9999694824219,21.1429080963135</latlng>
<latlng>81.9951629638672,21.1395511627198</latlng>
<latlng>81.9933166503907,21.1343898773194</latlng>
<latlng>81.9911727905274,21.1295604705811</latlng>
<latlng>81.9893112182618,21.1195507049561</latlng>
<latlng>81.9880905151367,21.0992908477784</latlng>
<latlng>81.9857177734376,21.0879096984864</latlng>
<latlng>81.9840469360352,21.0820198059083</latlng>
<latlng>81.9811019897462,21.0808200836182</latlng>
<latlng>81.9793319702149,21.0789909362794</latlng>
<latlng>81.9719161987305,21.0669898986818</latlng>
<latlng>81.9648513793946,21.0522403717042</latlng>
<latlng>81.9487686157227,21.0298881530762</latlng>
<latlng>81.9330902099609,21.0200328826904</latlng>
<latlng>81.9199066162111,21.0150794982911</latlng>
<latlng>81.9155960083008,21.012809753418</latlng>
<latlng>81.9020080566406,21.0005207061768</latlng>
<latlng>81.9008026123048,20.997859954834</latlng>
<latlng>81.8942260742188,20.9898605346681</latlng>
<latlng>81.8823318481446,20.9799728393555</latlng>
<latlng>81.8775024414063,20.9740791320801</latlng>
<latlng>81.8706665039064,20.9598999023439</latlng>
<latlng>81.8592071533204,20.9563503265381</latlng>
<latlng>81.8574066162109,20.9550704956055</latlng>
<latlng>81.8532714843751,20.9440708160401</latlng>
<latlng>81.8488311767578,20.9400501251221</latlng>
<latlng>81.8423690795898,20.9374904632569</latlng>
<latlng>81.8351593017579,20.9367294311523</latlng>
<latlng>81.830696105957,20.9372406005859</latlng>
<latlng>81.8178482055665,20.9450302124025</latlng>
<latlng>81.8108673095703,20.9432907104493</latlng>
<latlng>81.8092727661134,20.9467506408692</latlng>
<latlng>81.8100662231445,20.9504508972169</latlng>
<latlng>81.8098907470703,20.9545612335206</latlng>
<latlng>81.8077621459962,20.9573307037354</latlng>
<latlng>81.8035202026368,20.9601707458497</latlng>
<latlng>81.7982482910156,20.9623603820801</latlng>
<latlng>81.7911529541017,20.9619598388672</latlng>
<latlng>81.7797927856445,20.9637107849121</latlng>
<latlng>81.768409729004,20.9786796569825</latlng>
<latlng>81.7627868652344,20.9804306030274</latlng>
<latlng>81.7590560913087,20.9824600219727</latlng>
<latlng>81.758056640625,20.9893627166749</latlng>
<latlng>81.754035949707,20.9950008392334</latlng>
<latlng>81.7530822753906,20.9980506896973</latlng>
<latlng>81.7487716674805,21.0046710968018</latlng>
<latlng>81.7445297241212,21.0079212188721</latlng>
<latlng>81.7323989868165,21.0105018615723</latlng>
<latlng>81.7283782958986,21.0103626251221</latlng>
<latlng>81.7160568237305,21.006799697876</latlng>
<latlng>81.7130584716797,21.0067806243898</latlng>
<latlng>81.7115859985352,21.0075397491455</latlng>
<latlng>81.7069320678711,21.014310836792</latlng>
<latlng>81.7038879394531,21.0148696899413</latlng>
<latlng>81.7011795043945,21.014009475708</latlng>
<latlng>81.6965866088867,21.0097007751465</latlng>
<latlng>81.6920013427734,21.00172996521</latlng>
<latlng>81.6889572143554,21.0005702972412</latlng>
<latlng>81.685546875,21.0015907287599</latlng>
<latlng>81.6821670532227,20.9987983703613</latlng>
<latlng>81.6797561645509,20.9958610534669</latlng>
<latlng>81.6747589111329,20.9957294464112</latlng>
<latlng>81.6681823730469,20.9972190856933</latlng>
<latlng>81.6636962890626,20.9964294433594</latlng>
<latlng>81.654899597168,20.9967899322509</latlng>
<latlng>81.6523971557617,20.9962615966797</latlng>
<latlng>81.6491470336914,20.9985694885254</latlng>
<latlng>81.645606994629,21.0026092529298</latlng>
<latlng>81.6401214599609,21.0068893432617</latlng>
<latlng>81.6286392211915,21.0078296661378</latlng>
<latlng>81.6264572143555,21.009189605713</latlng>
<latlng>81.6247863769532,21.0114707946778</latlng>
<latlng>81.6182403564453,21.0147094726562</latlng>
<latlng>81.6149520874023,21.0178928375245</latlng>
<latlng>81.6125869750977,21.0188407897949</latlng>
<latlng>81.6066207885742,21.0236511230469</latlng>
<latlng>81.6017303466798,21.0282802581788</latlng>
<latlng>81.597038269043,21.0353507995607</latlng>
<latlng>81.5939025878907,21.0382194519044</latlng>
<latlng>81.5822372436524,21.0421810150147</latlng>
<latlng>81.5805969238282,21.0441608428955</latlng>
<latlng>81.5814590454102,21.0484085083009</latlng>
<latlng>81.5915222167969,21.0496902465821</latlng>
<latlng>81.5974426269531,21.0522193908691</latlng>
<latlng>81.6018829345704,21.0550384521485</latlng>
<latlng>81.6024475097657,21.0593395233155</latlng>
<latlng>81.599822998047,21.0636005401611</latlng>
<latlng>81.5961685180665,21.0649108886719</latlng>
<latlng>81.5873107910156,21.0659999847412</latlng>
<latlng>81.5837326049805,21.0672397613525</latlng>
<latlng>81.5766220092773,21.0699691772462</latlng>
<latlng>81.5736465454102,21.0718994140624</latlng>
<latlng>81.5726623535156,21.0741806030273</latlng>
<latlng>81.5733184814454,21.0843811035157</latlng>
<latlng>81.5710372924806,21.0927810668946</latlng>
<latlng>81.5741958618164,21.0982303619386</latlng>
<latlng>81.574951171875,21.104061126709</latlng>
<latlng>81.5759963989259,21.1060810089111</latlng>
<latlng>81.5769195556641,21.1221008300781</latlng>
<latlng>81.5806503295898,21.1296482086182</latlng>
<latlng>81.5850372314453,21.1340007781984</latlng>
<latlng>81.5896911621094,21.1408901214599</latlng>
<latlng>81.5994567871095,21.1474704742431</latlng>
<latlng>81.5994567871095,21.1576595306398</latlng>
<latlng>81.6026992797853,21.1592807769777</latlng>
<latlng>81.6175231933594,21.1600093841553</latlng>
<latlng>81.6117324829102,21.1698207855225</latlng>
<latlng>81.6081619262696,21.1782398223877</latlng>
<latlng>81.604217529297,21.1843299865722</latlng>
<latlng>81.6000366210939,21.1975612640381</latlng>
<latlng>81.5958328247071,21.2043628692627</latlng>
<latlng>81.5867767333984,21.2108097076416</latlng>
<latlng>81.5802383422851,21.2169227600099</latlng>
<latlng>81.5708999633789,21.2204704284669</latlng>
<latlng>81.5665664672852,21.2264518737794</latlng>
<latlng>81.5634918212891,21.2339801788331</latlng>
<latlng>81.5598068237306,21.2386684417725</latlng>
<latlng>81.5561828613282,21.2402019500733</latlng>
<latlng>81.5443878173828,21.2396297454835</latlng>
<latlng>81.5416564941407,21.2406406402588</latlng>
<latlng>81.5393829345704,21.2428703308107</latlng>
<latlng>81.5381164550781,21.2455596923829</latlng>
<latlng>81.5370483398438,21.2484092712403</latlng>
<latlng>81.5360870361329,21.2568111419679</latlng>
<latlng>81.5385131835938,21.2714710235596</latlng>
<latlng>81.5380706787111,21.2741508483888</latlng>
<latlng>81.5373229980468,21.2778797149659</latlng>
<latlng>81.5284729003907,21.296350479126</latlng>
<latlng>81.5275268554688,21.3008308410646</latlng>
<latlng>81.529769897461,21.3029193878173</latlng>
<latlng>81.5388031005861,21.3036785125733</latlng>
<latlng>81.5418167114258,21.3055305480958</latlng>
<latlng>81.5437316894532,21.3085403442384</latlng>
<latlng>81.5460205078126,21.3314304351807</latlng>
</coordinates>
